LICENSE
MANIFEST.in
README.md
setup.cfg
setup.py
thrift_explorer/__init__.py
thrift_explorer/communication_models.py
thrift_explorer/server.py
thrift_explorer/thrift_manager.py
thrift_explorer/thrift_models.py
thrift_explorer/thrift_parser.py
thrift_explorer/wsgi.py
thrift_explorer.egg-info/PKG-INFO
thrift_explorer.egg-info/SOURCES.txt
thrift_explorer.egg-info/dependency_links.txt
thrift_explorer.egg-info/requires.txt
thrift_explorer.egg-info/top_level.txt