Metadata-Version: 2.1
Name: thrift-explorer
Version: 0.8
Summary: Potentially useful utility for working with thrift files
Home-page: https://github.com/Bachmann1234/thriftExplorer
Author: Matt Bachmann
Author-email: bachmann.matt@gmail.com
License: GPLv3
Platform: UNKNOWN
Classifier: Intended Audience :: Developers
Classifier: License :: OSI Approved :: GNU General Public License v3 (GPLv3)
Classifier: Programming Language :: Python
Classifier: Programming Language :: Python :: 3
Classifier: Programming Language :: Python :: 3.7
Classifier: Programming Language :: Python :: Implementation :: CPython
Requires-Python: >=3.7.0
